python_lung_morphometrics/__init__.py
python_lung_morphometrics/_colocalization_analysis.py
python_lung_morphometrics/_do_mli.py
python_lung_morphometrics/_he_lung_injury_classification.py
python_lung_morphometrics/_utils.py
python_lung_morphometrics/cli.py
python_lung_morphometrics-0.4.0.dist-info/licenses/AUTHORS.rst
python_lung_morphometrics-0.4.0.dist-info/licenses/LICENSE
python_lung_morphometrics-0.4.0.dist-info/METADATA
python_lung_morphometrics-0.4.0.dist-info/WHEEL
python_lung_morphometrics-0.4.0.dist-info/entry_points.txt
python_lung_morphometrics-0.4.0.dist-info/top_level.txt
python_lung_morphometrics-0.4.0.dist-info/RECORD
