Metadata-Version: 2.4
Name: python_lung_morphometrics
Version: 0.4.0
Summary: A set of tools for measuring MLI and the like.
Author-email: "Sylvia N. Michki" <sylvia.michki@gmail.com>
Maintainer-email: "Sylvia N. Michki" <sylvia.michki@gmail.com>
License: GNU General Public License v3
Project-URL: bugs, https://github.com/sylviamic/python_lung_morphometrics/issues
Project-URL: changelog, https://github.com/sylviamic/python_lung_morphometrics/blob/master/changelog.md
Project-URL: homepage, https://github.com/sylviamic/python_lung_morphometrics
Classifier: Programming Language :: Python
Classifier: Development Status :: 4 - Beta
License-File: LICENSE
License-File: AUTHORS.rst
Requires-Dist: numpy>=2.0.0
Requires-Dist: pandas
Requires-Dist: scikit-image
Requires-Dist: scikit-learn
Requires-Dist: matplotlib
Requires-Dist: imageio
Requires-Dist: tifffile>=2025.2.18
Requires-Dist: imagecodecs
Requires-Dist: tqdm
Requires-Dist: skops
Requires-Dist: typer
Requires-Dist: pytest
Requires-Dist: tox
Requires-Dist: build
Requires-Dist: twine
Provides-Extra: dev
Requires-Dist: coverage; extra == "dev"
Requires-Dist: mypy; extra == "dev"
Requires-Dist: pytest; extra == "dev"
Requires-Dist: ruff; extra == "dev"
Provides-Extra: cellpose
Requires-Dist: cellpose; extra == "cellpose"
Dynamic: license-file
